CHANGES.txt
LICENSE.txt
MANIFEST.in
README.rst
setup.py
django_taggit_templatetags.egg-info/PKG-INFO
django_taggit_templatetags.egg-info/SOURCES.txt
django_taggit_templatetags.egg-info/dependency_links.txt
django_taggit_templatetags.egg-info/entry_points.txt
django_taggit_templatetags.egg-info/not-zip-safe
django_taggit_templatetags.egg-info/requires.txt
django_taggit_templatetags.egg-info/top_level.txt
taggit_templatetags/__init__.py
taggit_templatetags/models.py
taggit_templatetags/settings.py
taggit_templatetags/templatetags/__init__.py
taggit_templatetags/templatetags/taggit_extras.py
taggit_templatetags/tests/__init__.py
taggit_templatetags/tests/models.py
taggit_templatetags/tests/tests.py