Metadata-Version: 1.0
Name: django-taggit-templatetags
Version: 0.2.5
Summary: Templatetags for django-taggit.
Home-page: http://github.com/feuervogel/django-taggit-templatetags
Author: Julian Moritz
Author-email: jumo@gmx.de
License: BSD
Keywords: django taggit tags tagcloud taglist tagging tag
Platform: UNKNOWN
Classifier: Development Status :: 4 - Beta
Classifier: Environment :: Web Environment
Classifier: Intended Audience :: Developers
Classifier: License :: OSI Approved :: BSD License
Classifier: Operating System :: OS Independent
Classifier: Programming Language :: Python
Classifier: Framework :: Django
